{
  "name": "Leila Silva",
  "age": 45,
  "address": {
    "street": "Mefu Highway",
    "city": "Rozsusda",
    "state": "MD",
    "zip": "67717"
  },
  "contact": {
    "phone": "(975) 633-4546",
    "servicePhone": "800371532"
  },
  "birthday": "1995-02-17T19:44:55.789Z",
  "ip": "6.107.184.141",
  "foo": "bar",
  "profile": {
    "about": "It ru ojsu eve sumikisif muzweas eftoc zimsat go golek ji ho. Puvew res woma zenutowu awmiuz odig jurfeka gebu vazezloj ca hume fawfirzo ci reawi fafir. Bos jamso cuzi bupazwu kuj log kagkidmen fis nosursi wuotfe wuhopida liwnu nacukda sopwoz ma navat.",
    "bio": "Pinefcof firivos difa zuwjo abde fumme hacit lurahcik pawa tinagnol rasjafneb geculkaw. Polew sed gaoge rizku kutij cu vu rulo ve civ alilora ruf vem cer ruwe telufje. Datu mibo rod wupnocer nujeke ihoom oggij noj refadege bir cil ow daapik row kenetdam ari. Ovbuzmet omtu nikpew fi sor safizec oj oge huzzegja nigiici jufu ocajawat ladwiped ged moh niize efeul mocile."
  },
  "apiKey": "1c85a0072ab36e096d5b792c72b9c54995c8a51e830b3426103ff2c259891571",
  "currency": {
    "code": "SBD",
    "name": "Solomon Islands Dollar"
  }
}