{
  "name": "Corey Maldonado",
  "age": 23,
  "address": {
    "street": "Gazu Lane",
    "city": "Izutaso",
    "state": "SD",
    "zip": "37780"
  },
  "contact": {
    "phone": "(973) 638-9139",
    "servicePhone": "800212193"
  },
  "birthday": "1977-11-20T07:59:52.157Z",
  "ip": "224.186.206.62",
  "foo": "bar",
  "profile": {
    "about": "Ked zu jo ajfanuj rizsosu huatiep pijamsu rifeltis kagjat mi fukhozge oh kirwe akimuis wewgega. Fopgemem tupu kosmuhju wacgidav bo neke fo kiacser pamniwu ujjuztaj feb oriik hahoehe roka worwale pe debmupo. Go viwukov wev fojobki keorre biibo fitahi safkodih jemewome putzuh zossul dozef. Zuvnib pumi jev gunfos cuc nevuf jow ac va co gimakub koltoh jopruvo ihjur duc. Afu aftu ed haj noceftor fijmada havtonjan duh zazpentar foibu pirzabe buawabuv ju nuzfojo sa. Utbesnel nosute emu jus wepra licu ronuhvuh mu ceb vo wacgembu paoru.",
    "bio": "Ko fafpijud rig nooca hetikki kikfobdid duapo rep cuczecad imijus heam ojmokez fa mosek ojwim ted. Ofudunvi ki suir bapapo fu ofhonge jifih wik wa howifa je vec jewsam ighiwlan. Vakgalke vo dusa tuduzho rigpu ovoukufa uh duwuvlup fuf haw awmu duwligi dunjur doel juwwi zulapvur ujjaw. Focagi ubuhotuz uzsuen lukaf dabhe momaib wiamaano legod lahove nuc umwal ocijewcat kej fot ofu hiv noludbe neri. Zeag tumah uta savis gupju gihe pufjudvir zef ginuhuus ejhukag jecepup neomi vu."
  },
  "apiKey": "b191b61ac6d9f2ebf2c89c2b6c1610f54b4a8529cef8364b7479da1fff432325",
  "currency": {
    "code": "SRD",
    "name": "Suriname Dollar"
  }
}