{
  "name": "Polly Maxwell",
  "age": 31,
  "address": {
    "street": "Pufe Park",
    "city": "Pazumek",
    "state": "MS",
    "zip": "32777"
  },
  "contact": {
    "phone": "(244) 805-7493",
    "servicePhone": "800539618"
  },
  "birthday": "1988-07-18T03:32:57.250Z",
  "ip": "185.146.113.190",
  "foo": "bar",
  "profile": {
    "about": "Rafdezawo se potpolzaj tejpuda mo ruhus ropne go zatwajmi re cobnecor hi gow hubroik cafi. Te wiminon rovav fumarojil de puv bu iza boep resdiuli wo zopegmuf edilipev fegohej bizwovoh. Ze ukusoptu najvik warom zehbeg remsof garnotes uj fuk kufoliw ojibaoni zegugije tiwab sos fif. Fibujvol wuwgo ti dasjud ivo juv ob ku ho etadehel daleuli ku. Aroco kug ba nowkezi us corze ohilo aztuw cifu cilun oduhuc maeru se ocdu tital ahuvi towmigmik. Jugeznuk erasahan uggu suggikdir ha sogej wowsiz guhdo ro cibo new je. Ofucowe pakis eza diwo ci ob lekuhnak tuj aro levzawum dinzohi dijmahah map vos val.",
    "bio": "Cuvifav vizazev zasur nodacik nisepi alnimu leekon hok huan onilaj filmijuw cijdeczaf nufpogowo cojrunwon wam epeki ej. Biugakeb lolow cuwtuzoc ul jadposo piw soide nipra bekzamo hew geb zasace towab al ja. Wi wof kug fisadugi ku zo cujuh udojajbad hizikdu iceziti eztika camawnig lun."
  },
  "apiKey": "c68c9b4144e97786472e115d7c8775aac06f1a6e297639c809297d05a6f2e7a8",
  "currency": {
    "code": "CZK",
    "name": "Czech Republic Koruna"
  }
}