{
  "name": "Gary Summers",
  "age": 54,
  "address": {
    "street": "Vezza Highway",
    "city": "Lennutbec",
    "state": "WY",
    "zip": "03259"
  },
  "contact": {
    "phone": "(362) 382-6054",
    "servicePhone": "800411789"
  },
  "birthday": "1983-10-04T19:46:34.201Z",
  "ip": "143.244.170.77",
  "foo": "bar",
  "profile": {
    "about": "Dud opi ot pu geosdo enokiz adobig sobawe zatabav vo sazge izire dew. Bobbi fo vofado nemes toris jatu deeme onpus vogjug va gitipoj rikisvuf citi ik cutbujro bo. Winhavic ju kajodmag tuz neeto kavfi at luri zegkupci heczo huerka rot ike fasibiv. Tef ifki lodube picdacig tocfecwu hub ri vencel bajaw vut kuhiduvid we. La za ratoscer hug todvok cuwoke wig nuglaoza gu hiedu ewgagen modzo pefka widlab cifce hehe wotcoj kudhikam. Gusekapo rutucjew reunuvu zis umi lujoccud conuceso zu kiglu mesopgeg jitov faezuhu. Dezle fezbon lelut rirulipi de volibas nettolbok jifodane ar mucu jauzo tudub sicizfo.",
    "bio": "He cosi joj duzcov lolal zo id gifbaznuj jov mi ajukif buk tized lid socezoz gego mu. Bicig un es legpurvan ewisuktaz bonaj guicma pel tenijo ikdo tef himpuf hodeskih wewaruwaj gegma. Lu oliopioce nozudro barimad ajoda pahudon nobi ezbake pu ehu zawhevu fahfe lubolsuh. Fowda taet raib fuov vorcacdo ni eg zawod bisdonva diuz ga vote uvehule buovupo."
  },
  "apiKey": "7501b496a1a25cbfeedde0b0c53e498902a2572922e6d3439f51cde2f261bbd9",
  "currency": {
    "code": "LRD",
    "name": "Liberia Dollar"
  }
}